{"lituya": "li tu ya", "litva": "lit va", "litvac": "lit vac", "litvak": "lit vak", "litvaks": "lit vaks", "litvinov": "lit vi nov", "litvonov": "lit vo nov", "litynski": "li tyn ski", "litz": "litz", "litzi": "lit zi", "liuba": "liu ba", "liubimov": "liu bi mov", "liubinskas": "liu bin skas", "liubov": "liu bov", "liuchow": "liu chow", "liudger": "liud ger", "liudi": "liu di", "liue": "liu e", "liuerie": "liu e rie", "liuski": "liu ski", "liuti": "liu ti", "liutizi": "liu ti zi", "liuto": "liu to", "liv": "liv", "liv'ry": "liv 'ry", "livable": "liv a ble", "livadi": "li va di", "livadia": "li va di a", "livarot": "li va rot", "livatino": "li va ti no", "live": "live", "live'": "live '", "live-action": "live - ac tion", "live-aid": "live - aid", "live-and-let-live": "live - and - let - live", "live-born": "live - born", "live-in": "live - in", "live-wire": "live - wire", "live_up": "live _ up", "liveable": "live a ble", "livebearer": "live bear er", "livebearers": "live bear ers", "liveborn": "live born", "lived": "lived", "lived'": "lived '", "lived-in": "lived - in", "lived_up": "lived _ up", "livefood": "live food", "liveish": "live ish", "livelier": "live li er", "liveliest": "live li est", "livelihood": "live li hood", "livelihoods": "live li hoods", "liveliness": "live li ness", "livelong": "live long", "lively": "live ly", "liven": "liv en", "livened": "liv ened", "liveners": "liv en ers", "livening": "liv en ing", "livens": "liv ens", "liver": "liv er", "liver-": "liv er -", "liver-bowel": "liv er - bow el", "liver-stage": "liv er - stage", "liver-stage-specific": "liv er - stage - spe ci fic", "liveras": "li ve ras", "liverbus": "liv er bus", "liveried": "liv er ied", "liveries": "liv er ies", "liverish": "liv er ish", "liverman": "liv er man", "livermore": "liv er more", "liveron": "liv er on", "liverp": "liv er p", "liverpool": "liv er pool", "liverpool-based": "liv er pool - based", "liverpool-born": "liv er pool - born", "liverpudlian": "liv er pud li an", "liverpudlians": "liv er pud li ans", "livers": "liv ers", "liversedge": "liv ers edge", "liverton": "liv er ton", "liverwort": "liv er wort", "liverworts": "liv er worts", "livery": "liv er y", "liveryman": "liv er y man", "liverymen": "liv er y men", "lives": "lives", "lives-in": "lives - in", "livesey": "liv es ey", "liveseys": "liv es eys", "livesley": "liv es ley", "livest": "liv est", "livestock": "live stock", "liveth": "liv eth", "livett": "li vett", "livewire": "live wire", "livi": "li vi", "livia": "li vi a", "livid": "liv id", "lividity": "li vid i ty", "livigno": "li vig no", "livin'": "liv in '", "livin": "liv in", "living": "liv ing", "living-": "liv ing -", "living-in": "liv ing - in", "living-room": "liv ing - room", "living-rooms": "liv ing - rooms", "living_room": "liv ing _ room", "livings": "liv ings", "livingston": "liv ing ston", "livingstone": "liv ing stone", "livingstones": "liv ing stones", "livingstonii": "liv ing sto nii", "livinia": "li vi ni a", "livio": "li vi o", "liviu": "li viu", "livius": "li vi us", "livng": "liv ng", "livno": "liv no", "livock": "li vock", "livolsi": "li vol si", "livonia": "li vo ni a", "livonian": "li vo ni an", "livorne": "li vor ne", "livorno": "li vor no", "livox": "li vox", "livre": "li vre", "livres": "li vres", "livret": "li vret", "livrets": "li vrets", "livsey": "liv sey", "livulezi": "li vu le zi", "livvy": "liv vy", "livy": "li vy", "liwa": "li wa", "lix": "lix", "lixin": "li xin", "lixivia": "lix i vi a", "lixouri": "lix ou ri", "lixs": "lixs", "liyange": "li yan ge", "liyeko": "li ye ko", "liyf": "li yf", "liyun": "li yun", "liz": "liz", "liz'": "liz '", "liz's": "liz 's", "liz-beth": "liz - beth", "liza": "li za", "liza-lu": "li za - lu", "lizabeth": "liz a beth", "lizano": "li za no", "lizard": "liz ard", "lizard-hipped": "liz ard - hipped", "lizard-like": "liz ard - like", "lizardo": "li zar do", "lizards": "liz ards", "lizardy": "liz ard y", "lizars": "li zars", "lizaveta": "li za ve ta", "lizhi": "li zhi", "lizot": "li zot", "lizs": "lizs", "lizti": "liz ti", "lizz": "lizz", "lizzie": "liz zie", "lizzies": "liz zies", "lizzio": "liz zi o", "lizzy": "liz zy", "lj-c": "lj - c", "ljacic": "lja cic", "ljacii": "lja cii", "ljacil": "lja cil", "ljack": "ljack", "ljaclc": "lja clc", "ljacli": "lja cli", "ljacll": "lja cll", "ljadc": "lj adc", "ljadi": "lj adi", "ljadl": "lj adl", "ljb": "ljb", "ljc": "ljc", "ljiljana": "lji lja na", "ljj": "ljj", "ljkb": "ljkb", "ljotic": "ljo tic", "ljp": "ljp", "ljubic": "lju bic", "ljubisa": "lju bi sa", "ljubitza": "lju bit za", "ljubljana": "lju blja na", "ljubomir": "lju bo mir", "ljubov": "lju bov", "ljudevit": "lju de vit", "ljungh": "ljungh", "ljungman": "ljung man", "ljupco": "lju pco", "ljv": "ljv", "ljw": "ljw", "lk": "lk", "lkb": "lkb", "lke": "lke", "lkg": "lkg", "lkj": "lkj", "lkong": "l kong", "lkot": "l kot", "lkp": "lkp", "lla": "lla", "llacen": "lla cen", "llach": "llach", "llad": "llad", "lladro": "lla dro", "llaethog": "llae thog", "llaf": "llaf", "llagonne": "lla go nne", "llais": "llais", "llama": "lla ma", "llamas": "lla mas", "llambias": "llam bi as", "llan": "llan", "llanaber": "lla na ber", "llanbedr": "llan bedr", "llanberis": "llan be ris", "llanbers": "llan bers", "llanbrynmair": "llan bry n mair", "llandaff": "llan daff", "llandeilo": "llan dei lo", "llandewi": "llan de wi", "llandinam": "llan di nam", "llandovery": "llan do ve ry", "llandow": "llan dow", "llandre": "llan dre", "llandrindod": "llan drin dod", "llandrog": "llan drog", "llandsyl": "llan dy syl", "llandudno": "llan du dno", "llandyssul": "llan dy ssul", "llaneilian": "lla nei li an", "llanelli": "lla nel li", "llanelly": "lla nel ly", "llanelwedd": "lla nel wedd", "llaneros": "lla ne ros", "llanes": "lla nes", "llanfaes": "llan faes", "llanfair": "llan fair", "llanfairfechan": "llan fair fe chan", "llanfairpwll": "llan fair pwll", "llanfyllin": "llan fyl lin", "llangain": "llan gain", "llangan": "llan gan", "llangefni": "llan gef ni", "llangernyw": "llan ger nyw", "llangian": "llan gi an"}