{"oakheads": "oak heads", "oakheart": "oak heart", "oakhill": "oak hill", "oakhouse": "oak house", "oakhurst": "oak hurst", "oaking": "oak ing", "oakington": "oak ing ton", "oakland": "oak land", "oaklands": "oak lands", "oakle": "oak le", "oaklea": "oak lea", "oakleaf": "oak leaf", "oakleigh": "oak leigh", "oakley": "oak ley", "oakly": "oak ly", "oakman": "oak man", "oakmeeds": "oak meeds", "oakmere": "oak mere", "oakmont": "oak mont", "oakmoor": "oak moor", "oakmount": "oak mount", "oakport": "oak port", "oakridge": "oak ridge", "oaks": "oaks", "oaksey": "oak sey", "oaktree": "oak tree", "oakum": "oak um", "oakville": "oak ville", "oakwell": "oak well", "oakwood": "oak wood", "oakwoods": "oak woods", "oakworth": "oak worth", "oaky": "oak y", "oal": "oal", "oald": "oald", "oaldce": "oald ce", "oaldle": "oald le", "oalf": "oalf", "oamaru": "oa ma ru", "oamuru": "oa mu ru", "oan": "oan", "oancea": "oan ce a", "oanh": "oanh", "oany": "oa ny", "oanywy": "oa ny wy", "oao": "oao", "oap": "oap", "oap's": "oap's", "oapa": "oa pa", "oapart": "oa part", "oapec": "oa pec", "oaps": "oaps", "oar": "oar", "oar-like": "oar - like", "oare": "oare", "oared": "oared", "oares": "oares", "oarless": "oar less", "oarlock": "oar lock", "oarlocks": "oar locks", "oars": "oars", "oarsman": "oars man", "oarsmen": "oars men", "oas": "oas", "oasa": "oa sa", "oasaka": "oa sa ka", "oasal": "oa sal", "oase": "oa se", "oases": "oa ses", "oasig": "oa sig", "oasis": "oa sis", "oast": "oast", "oastler": "oast ler", "oasts": "oasts", "oasys": "oa sys", "oat": "oat", "oatbran": "oat bran", "oatcake": "oat cake", "oatcakes": "oat cakes", "oaten": "oat en", "oater": "oat er", "oates": "oates", "oatgrass": "oat grass", "oath": "oath", "oath-taking": "oath - tak ing", "oathing": "oath ing", "oaths": "oaths", "oatlands": "oat lands", "oatley": "oat ley", "oatmeal": "oat meal", "oatmealy": "oat meal y", "oatridge": "oat ridge", "oatrigg": "oat rigg", "oats": "oats", "oaty": "oat y", "oau": "oau", "oaxaca": "oax a ca", "oaxacan": "oax a can", "oaxters": "oax ters", "oay": "oay", "oaz": "oaz", "oba": "o ba", "obad": "o bad", "obadiah": "o ba di ah", "obadina": "o ba di na", "obafemi": "o ba fe mi", "obaid": "o baid", "obair": "o bair", "obama": "o ba ma", "obame": "o ba me", "obami": "o ba mi", "oban": "o ban", "obando": "o ban do", "obart": "o bart", "obas": "o bas", "obasanjo": "o ba san jo", "obat": "o bat", "obb": "obb", "obbedire": "ob be di re", "obbia": "ob bi a", "obbligato": "ob bli ga to", "obbo": "ob bo", "obc": "obc", "obconica": "ob co ni ca", "obd": "obd", "obdc": "ob dc", "obdef": "ob def", "obdt": "ob dt", "obducted": "ob duc ted", "obdulio": "ob du li o", "obduracy": "ob du ra cy", "obdurate": "ob du rate", "obdurately": "ob du rate ly", "obe": "obe", "obeah": "o be ah", "obebe": "o be be", "obeche": "o be che", "obecni": "o bec ni", "obect": "o bect", "obed": "o bed", "obedi": "o be di", "obedience": "o be di ence", "obedient": "o be di ent", "obediently": "o be di ent ly", "obeid": "o beid", "obeidat": "o bei dat", "obeidi": "o bei di", "obein": "o bein", "obeisance": "o bei sance", "obel": "o bel", "obelisk": "o be lisk", "obelisks": "o be lisks", "obelix": "o be lix", "obenault": "o be nault", "obeng": "o beng", "ober": "o ber", "oberammergau": "o ber am mer gau", "oberbaum": "o ber baum", "obere": "o be re", "oberei": "o be rei", "oberf": "o ber f", "oberg": "o berg", "obergr": "o ber g", "obergurgl": "o ber gur gl", "oberharz": "o ber harz", "oberhausen": "o ber hau sen", "oberheim": "o ber heim", "oberhuber": "o ber hu ber", "oberia": "o be ri a", "oberkirch": "o ber kirch", "oberl": "o ber l", "oberland": "o ber land", "oberle": "o ber le", "oberlin": "o ber lin", "oberm": "o berm", "oberoi": "o be roi", "oberon": "o be ron", "oberpr": "o ber pr", "obersee": "o ber see", "oberst": "o ber st", "oberstar": "o ber star", "obersturmfuhrer": "o ber sturm fuhr er", "obertass": "o ber tass", "obertor": "o ber tor", "oberwelt": "o ber welt", "obery": "o be ry", "oberzell": "o ber zell", "obes": "o bes", "obese": "o be se", "obesity": "o be si ty", "obetsibi": "o bet si bi", "obex": "o bex", "obey": "o bey", "obey-": "o bey -", "obeyance": "o bey ance", "obeyed": "o beyed", "obeying": "o bey ing", "obeys": "o beys", "obfuscate": "ob fus cate", "obfuscating": "ob fus cat ing", "obfuscation": "ob fus ca tion", "obfw": "ob fw", "obholzer": "ob hol zer", "obi": "o bi", "obiang": "o bi ang", "obidiah": "o bi di ah", "obidos": "o bi dos", "obie": "o bie", "obiit": "o bi it", "obili": "o bi li", "obiliary": "o bi lia ry", "obilitas": "o bi li tas", "obimpeh": "o bim peh", "obin": "o bin", "obina": "o bi na", "obins": "o bins", "obispal": "o bis pal", "obit": "o bit", "obiter": "o bi ter", "obits": "o bits", "obituaries": "o bi tu a ries", "obituary": "o bi tu a ry", "obizzi": "o biz zi", "obj": "obj", "obje": "ob je", "objec": "ob jec", "object": "ob ject", "object'": "ob ject '", "object-": "ob ject -", "object-based": "ob ject - based", "object-glass": "ob ject - glass", "object-linking": "ob ject - link ing", "object-orientation": "ob ject - or i en ta tion", "object-oriented": "ob ject - or i en ted", "object-relations": "ob ject - re la tions", "objectcenter": "ob ject cen ter", "objected": "ob ject ed", "objectification": "ob jec ti fi ca tion", "objectifications": "ob jec ti fi ca tions", "objectified": "ob jec ti fied", "objectifies": "ob jec ti fies", "objectify": "ob jec ti fy", "objectifying": "ob jec ti fy ing", "objectime": "ob jec time", "objecting": "ob ject ing", "objection": "ob jec tion", "objectionable": "ob jec tion a ble", "objections": "ob jec tions", "objectiq": "ob jec tiq", "objective": "ob jec tive", "objectively": "ob jec tive ly", "objectives": "ob jec tives", "objectivism": "ob jec ti vism", "objectivist": "ob jec ti vist", "objectivity": "ob jec ti vi ty", "objector": "ob jec tor", "objectors": "ob jec tors", "objects": "ob jects", "objectstore": "ob ject store", "objectual": "ob jec tu al", "objectworks": "ob ject works", "objet": "ob jet", "objet_d'art": "ob jet _ d'art", "objets": "ob jets", "objets_d'art": "ob jets _ d'art", "obl": "ob l", "oblast": "ob last", "oblasti": "ob las ti", "oblasts": "ob lasts", "oblate": "ob late", "oblation": "ob la tion", "oblatz": "ob latz", "oble": "ob le", "obler": "ob ler", "obli": "ob li", "oblidge": "ob lidge", "oblidged": "ob lidged", "obliga": "ob li ga", "obligate": "ob li gate", "obligated": "ob li ga ted", "obligation": "ob li ga tion", "obligations": "ob li ga tions", "obligato": "ob li ga to", "obligatoriness": "ob li ga to ri ness", "oblige": "ob lige", "obliged": "ob liged", "obligee": "ob li gee", "obliges": "ob liges", "obligin'": "ob li gin'", "obliging": "ob li ging", "obligingly": "ob li ging ly", "obligor": "ob li gor", "oblique": "ob lique", "oblique-slip": "ob lique - slip", "obliquely": "ob lique ly", "obliques": "ob liques", "obliquity": "ob li qui ty", "obliquum": "ob li quum", "obliquus": "ob li quus", "obliterans": "ob li te rans", "obliterate": "ob li te rate", "obliterated": "ob li te ra ted", "obliterates": "ob li te rates", "obliterating": "ob li te ra ting", "obliteration": "ob li te ra tion", "obliv": "ob liv", "oblivion": "ob li vi on", "oblivious": "ob li vi ous", "obloha": "ob lo ha", "oblong": "ob long", "oblongs": "ob longs", "obloquy": "ob lo quy", "oblt": "ob lt", "obman": "ob man", "obn": "ob n", "obnoxious": "ob no xious", "obnoxiously": "ob no xious ly", "obo": "ob o", "obock": "ob ock", "obod": "ob od", "oboe": "ob oe", "oboe-led": "ob oe - led", "oboeist": "ob oe ist", "oboes": "ob oes", "oboist": "ob o ist", "oboists": "ob o ists", "obok": "ob ok", "obol": "ob ol", "obolensky": "ob o len sky", "obols": "ob ols", "obong": "ob ong", "oborknez": "ob or knez", "oborony": "ob o ro ny", "obote": "ob o te", "obous": "ob ous", "obra": "ob ra", "obrador": "ob ra dor", "obradovi": "ob ra do vi", "obras": "ob ras", "obrazova": "ob ra zo va", "obrecht": "ob recht", "obree": "ob ree", "obreg": "ob reg", "obrenovi": "ob re no vi", "obrera": "ob re ra", "obreras": "ob re ras", "obrero": "ob re ro", "obreroi": "ob re roi", "obreros": "ob re ros", "obrok": "ob rok", "obruchev": "ob ru chev", "obs": "ob s", "obscene": "ob scene", "obscenely": "ob sce ne ly", "obscenities": "ob sce ni ties", "obscenity": "ob sce ni ty", "obscura": "ob scu ra", "obscurantism": "ob scu ran tism", "obscurantist": "ob scu ran tist", "obscuras": "ob scu ras", "obscure": "ob scure", "obscured": "ob scured", "obscurely": "ob scure ly", "obscurer": "ob scu rer", "obscures": "ob scures", "obscuring": "ob scu ring", "obscurities": "ob scu ri ties", "obscurity": "ob scu ri ty", "obscurus": "ob scu rus", "obselete": "ob se lete", "obsequies": "ob se quies", "obsequious": "ob se qui ous", "obsequiously": "ob se qui ous ly", "obser": "ob ser", "obsert": "ob sert", "observ": "ob serv", "observa": "ob ser va", "observable": "ob ser va ble", "observables": "ob ser va bles", "observance": "ob ser vance", "observances": "ob ser vances", "observant": "ob ser vant", "observat": "ob ser vat", "observation": "ob ser va tion", "observational": "ob ser va tion al", "observationally": "ob ser va tion al ly", "observations": "ob ser va tions", "observatories": "ob ser va to ries", "observatory": "ob ser va to ry", "observe": "ob serve", "observe'": "ob serve'", "observer": "ob ser ver", "observers": "ob ser vers", "observes": "ob serves", "observing": "ob ser ving", "obses": "ob ses", "obsess": "ob sess", "obsessed": "ob sessed", "obsesses": "ob sesses", "obsession": "ob ses sion", "obsessional": "ob ses sion al", "obsessionally": "ob ses sion al ly", "obsessions": "ob ses sions", "obsessive": "ob ses sive", "obsessive-compulsive": "ob ses sive - com pul sive", "obsessively": "ob ses sive ly", "obsessiveness": "ob ses sive ness", "obsessives": "ob ses sives", "obsidian": "ob si di an", "obsolescence": "ob so les cence", "obsolescent": "ob so les cent", "obsoleta": "ob so le ta", "obsolete": "ob so lete", "obsolute": "ob so lute", "obstacle": "ob sta cle", "obstacles": "ob sta cles", "obstat": "ob stat", "obstetric": "ob ste tric", "obstetrical": "ob ste tri cal", "obstetrician": "ob ste tri cian", "obstetricians": "ob ste tri cians", "obstetrics": "ob ste trics", "obstinacy": "ob sti na cy", "obstinate": "ob sti nate", "obstinately": "ob sti nate ly", "obstreperous": "ob stre pe rous", "obstruct": "ob struct", "obstructed": "ob struc ted", "obstructing": "ob struc ting", "obstruction": "ob struc tion", "obstructionism": "ob struc tion ism", "obstructionist": "ob struc tion ist", "obstructions": "ob struc tions", "obstructive": "ob struc tive", "obstructs": "ob structs", "obstruent": "ob stru ent", "obtain": "ob tain", "obtain'": "ob tain'", "obtainable": "ob tain a ble", "obtained": "ob tained", "obtaining": "ob tain ing", "obtains": "ob tains", "obtrude": "ob trude", "obtruded": "ob trud ed", "obtrudes": "ob trudes", "obtrusive": "ob tru sive", "obtunema": "ob tu ne ma", "obtusa": "ob tu sa", "obtuse": "ob tuse", "obtusely": "ob tuse ly", "obtuseness": "ob tuse ness", "obuchi": "ob u chi", "obukhov": "ob u khov", "obukw": "ob u kw", "obuzuni": "ob u zu ni", "obv": "ob v", "obverse": "ob verse", "obvi": "ob vi", "obviate": "ob vi ate", "obviated": "ob vi a ted", "obviates": "ob vi ates", "obviating": "ob vi a ting", "obviosly": "ob vi os ly", "obviou": "ob vi ou", "obvious": "ob vi ous", "obviously": "ob vi ous ly", "obviousness": "ob vi ous ness", "obvously": "ob vious ly", "oby": "ob y", "obyns": "ob yns", "oca": "o ca", "oca-cola": "o ca - co la", "ocadu": "o ca du", "ocalan": "o ca lan", "ocampo": "o cam po", "ocao": "o cao", "ocarina": "o ca ri na", "ocarinas": "o ca ri nas", "ocasek": "o ca sek", "ocassion": "o cas sion", "occa": "o cca", "occab": "o c cab", "occam": "o ccam", "occas": "o ccas", "occasion": "o cca sion", "occasion-setting": "o cca sion - set ting", "occasioned": "o cca sioned", "occasioning": "o cca sion ing", "occasions": "o cca sions", "occhetto": "o cchet to", "occhi": "o cchi", "occi": "o cci", "occident": "o cci dent", "occidental": "o cci den tal", "occidentale": "o cci den ta le", "occidentalis": "o cci den ta lis", "occipital": "o cci pi tal", "occipito": "o cci pi to", "occiput": "o cci put", "occitan": "o cci tan", "occlude": "o cclude", "occluded": "o cclu ded", "occluder": "o cclu der", "occludes": "o ccludes", "occluding": "o cclu ding", "occlusal": "o cclu sal", "occlusion": "o cclu sion", "occlusive": "o cclu sive", "occu": "o ccu", "occulobe": "o ccu lo be", "occult": "o ccult", "occulta": "o ccul ta"}