{"vocals": "vo cals", "vocaltec": "vo cal tec", "vocation": "vo ca tion", "vocational": "vo ca tion al", "vocationalism": "vo ca tion al ism", "vocationally": "vo ca tion al ly", "vocations": "vo ca tions", "vocative": "vo ca tive", "vocatives": "vo ca tives", "vocatus": "vo ca tus", "voce": "vo ce", "vocem": "vo cem", "voces": "vo ces", "voci": "vo ci", "vocibus": "vo ci bus", "vociferous": "vo cif er ous", "vociferously": "vo cif er ous ly", "vockins": "vock ins", "vocoder": "vo co der", "vocouma": "vo cou ma", "vocs": "vocs", "vocum": "vo cum", "vod": "vod", "voda": "vo da", "vodac": "vo dac", "vodafax": "vo da fax", "vodafone": "vo da fone", "vodapage": "vo da page", "vodaphone": "vo da phone", "vodata": "vo da ta", "voddies": "vod dies", "voden": "vo den", "voder": "vo der", "vodicka": "vo dick a", "vodka": "vod ka", "vodkas": "vod kas", "vodnik": "vod nik", "vodoun": "vo doun", "voe": "voe", "voegelin": "voe ge lin", "voelcker": "voel cker", "voelker": "voel ker", "voelkle": "voel kle", "voeller": "voel ler", "voena": "voe na", "voennaia": "voe nna ia", "voennoe": "voe nnoe", "voennogo": "voe nno go", "voes": "voes", "voet": "vo et", "voeux": "voeux", "voevoda": "voe vo da", "voevody": "voe vo dy", "vog": "vog", "vogae": "vo gae", "vogan": "vo gan", "vogel": "vo gel", "vogeler": "vo ge ler", "vogelh": "vo gel h", "vogels": "vo gels", "vogelsang": "vo gel sang", "vogelstein": "vo gel stein", "voget": "vo get", "vogl": "vo gl", "vogler": "vo gler", "vogon": "vo gon", "vogosca": "vo gos ca", "vogt": "vogt", "vogtland": "vogt land", "vogts": "vogts", "vogue": "vogue", "vogued": "vogued", "vogueing": "vogue ing", "voguer": "vogu er", "vogues": "vogues", "voguish": "vogu ish", "vohmer": "voh mer", "vohumana": "vo hu ma na", "voi": "voi", "voice'": "voice '", "voice-activated": "voice - ac ti va ted", "voice-mail": "voice - mail", "voice-over": "voice - o ver", "voice-overs": "voice - o vers", "voice-we": "voice - we", "voicebox": "voice box", "voicein": "voice in", "voiceless": "voice less", "voicemail": "voice mail", "voiceover": "voice o ver", "voicer": "voic er", "voices": "voic es", "voicetype": "voice type", "voici": "voi ci", "voicing": "voic ing", "voicings": "voic ings", "voidable": "void a ble", "voidance": "void ance", "voided": "void ed", "voider": "void er", "voiders": "void ers", "voiding": "void ing", "voidless": "void less", "voidness": "void ness", "voidoids": "void oids", "voids": "voids", "voie": "voie", "voient": "voi ent", "voight": "voight", "voigle": "voi gle", "voigny": "voi gny", "voigt": "voigt", "voil": "voil", "voila": "voi la", "voile": "voile", "voiles": "voiles", "voilla": "voil la", "voipreux": "voi preux", "voir": "voir", "voire": "voi re", "voiron": "voi ron", "vois": "vois", "voisin": "voi sin", "voith": "voith", "voiture": "voi ture", "voivode": "voi vode", "voix": "voix", "vojanovy": "vo ja no vy", "vojislav": "vo ji slav", "vojt": "vojt", "vojta": "voj ta", "vojtech": "voj tech", "vojvoda": "voj vo da", "vojvodina": "voj vo di na", "vokani": "vo ka ni", "vokes": "vo kes", "vokins": "vo kins", "vol'sky": "vol 'sky", "vol-": "vol -", "vol-au-vent": "vol - au - vent", "vol-au-vents": "vol - au - vents", "volac": "vo lac", "volador": "vo la dor", "volage": "vo lage", "volagir": "vo la gir", "volanic": "vo la nic", "volans": "vo lans", "volansky": "vo lan sky", "volant": "vo lant", "volante": "vo lan te", "volants": "vo lants", "volapuke": "vo la puke", "volare": "vo la re", "volarome": "vo la rome", "volatil": "vo la til", "volatile": "vo la tile", "volatile-rich": "vo la tile - rich", "volatiles": "vo la tiles", "volatility": "vo la til i ty", "volatility-maturity": "vo la til i ty - ma tu ri ty", "volcae": "vol cae", "volcan": "vol can", "volcane": "vol cane", "volcanes": "vol canes", "volcanic": "vol can ic", "volcanicity": "vol ca nic i ty", "volcaniclastic": "vol ca ni clas tic", "volcanics": "vol can ics", "volcanism": "vol ca nism", "volcano": "vol ca no", "volcanoes": "vol ca noes", "volcanogenic": "vol ca no gen ic", "volcanology": "vol ca nol o gy", "volcanos": "vol ca nos", "volcans": "vol cans", "volcker": "vol cker", "volcow": "vol cow", "volcuf": "vol cuf", "vold": "vold", "vole": "vole", "volea": "vo lea", "volees": "vo lees", "volemic": "vo le mic", "volendam": "vo len dam", "volens": "vo lens", "volente": "vo len te", "volenti": "vo len ti", "voleris": "vo le ris", "voles": "voles", "volex": "vo lex", "volf": "volf", "volga": "vol ga", "volgar": "vol gar", "volgian": "vol gi an", "volgograd": "vol go grad", "volhard": "vol hard", "voli": "vo li", "volicer": "vo li cer", "volid": "vo lid", "voliera": "vo li e ra", "volitans": "vo li tans", "volition": "vo li tion", "volitional": "vo li tion al", "volitis": "vo li tis", "voljc": "vol jc", "volk": "volk", "volkani": "vol ka ni", "volkart": "vol kart", "volke": "vol ke", "volkelt": "vol kelt", "volken": "vol ken", "volker": "vol ker", "volkhov": "vol khov", "volkish": "vol kish", "volkist": "vol kist", "volkl": "vol kl", "volkmar": "vol k mar", "volkoff": "vol koff", "volkov": "vol kov", "volkova": "vol ko va", "volkovs": "vol kovs", "volks": "volks", "volks-": "volks -", "volksfront": "volks front", "volksgerichte": "volks ge rich te", "volkskammer": "volks kam mer", "volksoper": "volks o per", "volkspartei": "volks par tei", "volkspartij": "volks par tij", "volkst": "volk st", "volkstag": "volks tag", "volksunie": "volks u nie", "volkswagen": "volks wa gen", "volkswagens": "volks wa gens", "volkwein": "volk wein", "voll": "voll", "vollam": "vol lam", "vollan": "vol lan", "vollard": "vol lard", "voller": "vol ler", "volley": "vol ley", "volleyball": "vol ley ball", "volleyed": "vol leyed", "volleyer": "vol ley er", "volleying": "vol ley ing", "volleys": "vol leys", "vollore": "vol lore", "vollrath": "vol lrath", "vollst": "voll st", "volly": "vol ly", "volmac": "vol mac", "volmer": "vol mer", "volmet": "vol met", "volna": "vol na", "volney": "vol ney", "volo": "vo lo", "volodia": "vo lo dia", "volodya": "vo lo dya", "vologsky": "vo log sky", "volont": "vo lont", "volopen": "vo lo pen", "volos": "vo los", "voloshin": "vo lo shin", "volost": "vo lost", "volost'": "vo lost '", "volosti": "vo los ti", "volpe": "vol pe", "volpedo": "vol pe do", "volpes": "vol pes", "volpi": "vol pi", "volpone": "vol po ne", "vols": "vols", "volsec": "vol sec", "volsky": "vol sky", "volstad": "vol stad", "volstead": "vol stead", "volsung": "vol sung", "volsungs": "vol sungs", "volta": "vol ta", "voltage": "volt age", "voltages": "volt ag es", "voltai": "vol tai", "voltaic": "vol ta ic", "voltaire": "vol taire", "voltarol": "vol ta rol", "volte": "vol te", "volte-": "vol te -", "volte-face": "vol te - face", "volte_face": "vol te _ face", "volterra": "vol ter ra", "voltmann": "volt mann", "voltmeter": "volt me ter", "volto": "vol to", "volts": "volts", "volturno": "vol tur no", "voluble": "vol u ble", "volubly": "vol u bly", "voluem": "vo lu em", "voluerit": "vo lu e rit", "volumatic": "vo lu mat ic", "volume-": "vol ume -", "volumed": "vol umed", "volumes": "vol umes", "volumetric": "vol u met ric", "volumina": "vo lu mi na", "voluminous": "vo lu mi nous", "volumise": "vol u mise", "volumising": "vol u mis ing", "volumnia": "vo lum nia", "volun": "vo lun", "volunt": "vo lun t", "voluntaries": "vol un ta ries", "voluntarily": "vol un ta ri ly", "voluntariness": "vol un ta ri ness", "voluntarism": "vol un ta rism", "voluntarist": "vol un ta rist", "voluntaristic": "vol un ta ris tic", "voluntary": "vol un ta ry", "voluntary-aided": "vol un ta ry - ai ded", "voluntaryism": "vol un ta ry ism", "voluntas": "vo lun tas", "volunteer": "vol un teer", "volunteered": "vol un teered", "volunteering": "vol un teer ing", "volunteers": "vol un teers", "volupeer": "vo lu peer", "volupine": "vo lu pine", "volupt": "vo lupt", "volupte": "vo lup te", "voluptua": "vo lup tu a", "voluptuary": "vo lup tu a ry", "voluptuous": "vo lup tu ous", "voluptuously": "vo lup tu ous ly", "voluptuousness": "vo lup tu ous ness", "voluta": "vo lu ta", "volute": "vo lute", "voluted": "vo lut ed", "volutes": "vo lutes", "voluting": "vo lut ing", "volver": "vol ver", "volvic": "vol vic", "volvo": "vol vo", "volvos": "vol vos", "volvox": "vol vox", "volvulus": "vol vu lus", "volx": "volx", "volyen": "vol yen", "volyers": "vol yers", "volynsk": "vo lyn sk", "volynsky": "vo lyn sky", "vom": "vom", "vomero": "vo me ro", "vomica": "vo mi ca", "vomit": "vom it", "vomited": "vom it ed", "vomiting": "vom it ing", "vomitous": "vom i tous", "vomits": "vom its", "vomitus": "vom i tus", "vommy": "vom my", "von": "von", "vonadk": "von adk", "voncken": "von cken", "vondelpark": "von del park", "vondra": "von dra", "vonetta": "vo net ta", "vongara": "von ga ra", "vongkhamsao": "von gkham sao", "vongole": "von go le", "vongphet": "von g phet", "vongs": "vongs", "vongvichit": "von gvi chit", "vonjy": "von jy", "vonk": "vonk", "vonla": "von la", "vonnas": "von nas", "vonnegut": "von ne gut", "vons": "vons", "vont": "vont", "vontobel": "von to bel", "vony": "vo ny", "voodism": "voo dism", "voodoo": "voo doo", "voodoos": "voo doos", "vookodlaks": "voo ko dlaks", "voomf": "voomf", "voor": "voor", "voord": "voord", "voorhees": "voor hees", "voorhies": "voor hies", "voorhout": "voor hout", "voors": "voors", "voort": "voort", "voov": "voov", "vopo": "vo po", "vopos": "vo pos", "vor": "vor", "vor-": "vor -", "vora": "vo ra", "voracious": "vo ra cious", "voraciously": "vo ra cious ly", "voracity": "vo rac i ty", "voragine": "vo ra gi ne", "voranart": "vo ra nart", "vorarlberg": "vo rarl berg", "vorax": "vo rax", "vorbach": "vor bach", "vord": "vord", "vorderman": "vor der man", "vorghan": "vor ghan", "voris": "vo ris", "vork": "vork", "vorkuta": "vor ku ta", "vorlager": "vor la ger", "vorlich": "vor lich", "vormund": "vor mund", "vorobiev": "vo ro biev", "vorobyov": "vo ro byov", "voronezh": "vo ro nezh", "voronin": "vo ro nin", "voronina": "vo ro ni na", "voronkov": "vo ron kov", "voronov": "vo ro nov", "voronov-vaux": "vo ro nov - vaux", "voronovs": "vo ro novs", "vorontseff": "vo ront seff", "vorontsov": "vo ront sov", "vorota": "vo ro ta", "vorou": "vo rou", "vorpal": "vor pal", "vorrsa": "vor rsa", "vorry": "vor ry", "vorse": "vorse", "vorshgar": "vor sh gar", "vorsprung": "vor sprung", "vorst": "vorst", "vorstadt": "vor stadt", "vorster": "vor ster", "vortac": "vor tac", "vortai": "vor tai", "vortec": "vor tec", "vortex": "vor tex", "vortexed": "vor texed", "vortexes": "vor tex es", "vortexing": "vor tex ing", "vortical": "vor ti cal", "vortice": "vor ti ce", "vortices": "vor ti ces", "vorticist": "vor ti cist", "vorticity": "vor tic i ty", "vortigern": "vor ti gern", "vortism": "vor tism", "vortoil": "vor toil", "vorw": "vorw", "vorwelt": "vor welt", "vorwish": "vor wish", "vos": "vos", "vose": "vose", "vosges": "vos ges", "voskepar": "vos ke par", "vosm": "vosm", "vosper": "vos per", "voss": "voss", "vossen": "vos sen", "vostell": "vos tell", "vostok": "vos tok", "vostre": "vos tre", "vostro": "vos tro", "vosts": "vosts", "vot": "vot", "votadini": "vo ta di ni", "votaries": "vo ta ries", "votary": "vo ta ry", "votchina": "vot chi na", "vote'": "vote '", "vote-buying": "vote - buy ing", "vote-catching": "vote - catch ing", "vote-guidance": "vote - guid ance", "vote-rigging": "vote - rig ging", "vote-winner": "vote - win ner", "vote-winning": "vote - win ning", "voted": "vot ed", "voteless": "vote less", "voter": "vot er", "voters": "vot ers", "votes_at": "votes _ at", "votez": "vo tez", "voth": "voth", "votive": "vo tive", "votively": "vo tive ly", "votives": "vo tives", "votkinsk": "vot kin sk", "voto": "vo to", "votos": "vo tos", "votre": "vo tre", "votro": "vo tro", "vou": "vou", "vouce": "vouce", "vouch": "vouch", "vouched": "vouched", "voucher": "vouch er", "vouchers": "vouch ers", "vouches": "vouch es", "vouching": "vouch ing", "vouchsafe": "vouch safe", "vouchsafed": "vouch safed", "voudrait": "vou drait", "voudras": "vou dras", "vouet": "vou et", "vought": "vought", "vouill": "vou ill", "voukashan": "vou ka shan"}