{"chandana": "chan da na", "chandelier": "chan de lier", "chandeliers": "chan de liers", "chander": "chan der", "chandio": "chan dio", "chandler": "chan dler", "chandlers": "chan dlers", "chandlery": "chan dlery", "chandley": "chan dley", "chandni": "chan dni", "chandon": "chan don", "chandos": "chan dos", "chandra": "chan dra", "chandran": "chan dran", "chandrasekhar": "chan dra se khar", "chandris": "chan dris", "chandu": "chan du", "chane": "cha ne", "chanel": "cha nel", "chanes": "cha nes", "chanet": "cha net", "chaneuon": "cha neu on", "chaney": "cha ney", "chang'an": "chang ' an", "changan": "chan gan", "change-over": "change - o ver", "changeability": "change a bi li ty", "changeable": "change a ble", "changeless": "change less", "changeling": "change ling", "changelings": "change lings", "changeover": "change o ver", "changer": "chan ger", "changers": "chan gers", "changes": "chan ges", "changeth": "chan geth", "changey": "chan gey", "changez": "chan gez", "changi": "chan gi", "changin": "chan gin", "changin'": "chan gin '", "changing": "chan ging", "changing-room": "chan ging - room", "changing-rooms": "chan ging - rooms", "changs": "changs", "changsha": "chang sha", "changtse": "chang tse", "changve": "chang ve", "chani": "cha ni", "chania": "cha nia", "chanine": "cha nine", "chanka": "chan ka", "channa": "chan na", "channals": "chan nals", "channell": "chan nell", "channelled": "chan nelled", "channelling": "chan nel ling", "channels": "chan nels", "channer": "chan ner", "channi": "chan ni", "channing": "chan ning", "channings": "chan nings", "channon": "chan non", "chano": "cha no", "chanoine": "cha noine", "chanonry": "cha non ry", "chanoun": "cha noun", "chanoyu": "cha no yu", "chans": "chans", "chanson": "chan son", "chansons": "chan sons", "chant": "chant", "chantal": "chan tal", "chantant": "chan tant", "chanted": "chant ed", "chantel": "chan tel", "chantelle": "chan telle", "chantent": "chan tent", "chanter": "chan ter", "chanterelle": "chan te relle", "chanterelles": "chan te relles", "chanters": "chan ters", "chanteur": "chan teur", "chanteuse": "chan teuse", "chanthu": "chan thu", "chantier": "chan tier", "chantiers": "chan tiers", "chantilly": "chan til ly", "chantin'": "chan tin '", "chanting": "chan ting", "chantler": "chan tler", "chanto": "chan to", "chantrell": "chan trell", "chantrey": "chan trey", "chantries": "chan tries", "chantry": "chan try", "chants": "chants", "chanty": "chan ty", "chanukah": "cha nu kah", "chanzoni": "chan zo ni", "chanzy": "chan zy", "chao": "cha o", "chaolais": "cha o lais", "chaology": "cha o lo gy", "chaorach": "cha o rach", "chaos": "cha os", "chaot": "cha ot", "chaotic": "cha o tic", "chaotically": "cha o ti cal ly", "chaouat": "cha ou at", "chaouen": "cha ou en", "chaovalit": "cha o va lit", "chaozhu": "cha o zhu", "chap": "chap", "chapals": "cha pals", "chapanis": "cha pa nis", "chapare": "cha pa re", "chapati": "cha pa ti", "chapatis": "cha pa tis", "chapatti": "cha pat ti", "chapattis": "cha pat tis", "chapbook": "chap book", "chape": "chape", "chapeau": "cha peau", "chapei": "cha pei", "chapel": "cha pel", "chapel-en-le-frith": "cha pel - en - le - frith", "chapel-going": "cha pel - go ing", "chapel-le-dale": "cha pel - le - dale", "chapelcross": "cha pel cross", "chapelet": "cha pe let", "chapell": "cha pell", "chapelle": "cha pelle", "chapelle-charbons": "cha pelle - char bons", "chapelon": "cha pe lon", "chapelry": "cha pel ry", "chapels": "cha pels", "chapelton": "cha pel ton", "chapeltown": "cha pel town", "chaper": "cha per", "chaperon": "cha pe ron", "chaperonage": "cha pe ron age", "chaperone": "cha pe rone", "chaperoned": "cha pe roned", "chaperoning": "cha pe ron ing", "chaperons": "cha pe rons", "chapes": "cha pes", "chapess": "cha pess", "chapham": "cha pham", "chaphood": "chap hood", "chapieux": "cha pieux", "chapin": "cha pin", "chapius": "cha pius", "chapka": "chap ka", "chaplain": "chap lain", "chaplaincy": "chap lain cy", "chaplains": "chap lains", "chaplais": "cha plais", "chaplet": "chap let", "chaplets": "chap lets", "chaplin": "chap lin", "chaplin-": "chap lin -", "chaplins": "chap lins", "chapman": "chap man", "chapmans": "chap mans", "chapmen": "chap men", "chapone": "cha pone", "chapot": "cha pot", "chappals": "chap pals", "chapped": "chapped", "chappel": "chap pel", "chappell": "chap pell", "chappen": "chap pen", "chappens": "chap pens", "chappers": "chap pers", "chappie": "chap pie", "chappies": "chap pies", "chappill": "chap pill", "chapping": "chap ping", "chapple": "chap ple", "chapple-hyam": "chap ple - hy am", "chappo": "chap po", "chappy": "chap py", "chappys": "chap pys", "chaprassi": "chap ras si", "chaps": "chaps", "chapska": "chaps ka", "chapson": "chap son", "chapt": "chapt", "chaptal": "chap tal", "chapter": "chap ter", "chapterhouse": "chap ter house", "chapters": "chap ters", "chapuis": "cha puis", "chapuisat": "cha pui sat", "chaque": "cha que", "char": "char", "chara": "cha ra", "charabanc": "cha ra banc", "charabancs": "cha ra bancs", "charac": "cha rac", "characid": "cha ra cid", "characin": "cha ra cin", "characins": "cha ra cins", "character-based": "cha rac ter - based", "character-building": "cha rac ter - buil ding", "character-drawing": "cha rac ter - dra wing", "character-forming": "cha rac ter - for ming", "characterful": "cha rac ter ful", "characterisation": "cha rac te ri sa tion", "characterisations": "cha rac te ri sa tions", "characterise": "cha rac te rise", "characterised": "cha rac te rised", "characterises": "cha rac te rises", "characterising": "cha rac te ri sing", "characteristic": "cha rac te ris tic", "characteristically": "cha rac te ris ti cal ly", "characteristics": "cha rac te ris tics", "characterization": "cha rac te ri za tion", "characterizations": "cha rac te ri za tions", "characterize": "cha rac te rize", "characterized": "cha rac te rized", "characterizes": "cha rac te rizes", "characterizing": "cha rac te ri zing", "characterless": "cha rac ter less", "charade": "cha rade", "charades": "cha rades", "charadrius": "cha ra dri us", "charan": "cha ran", "charando": "cha ran do", "charanga": "cha ran ga", "charango": "cha ran go", "chararic": "cha ra ric", "charas": "cha ras", "charasse": "cha rasse", "charater": "cha ra ter", "charbonni": "char bon ni", "charbury": "char bu ry", "charcas": "char cas", "charcoal": "char coal", "charcoal-burners": "char coal - bur ners", "charcoal-grey": "char coal - grey", "charcoaled": "char coaled", "charcoals": "char coals", "charcol": "char col", "charcot": "char cot", "charcuterie": "char cu te rie", "charcuti": "char cu ti", "charcutier": "char cu tier", "chard": "chard", "charde": "char de", "chardell": "char dell", "chardin": "char din", "chardonnay": "char don nay", "chardonnays": "char don nays", "chare": "cha re", "chareau": "char eau", "charef": "char ef", "chareges": "char e ges", "charemza": "char em za", "charente": "char en te", "charents": "char ents", "charest": "char est", "chareyon": "char ey on", "charfi": "char fi", "charfield": "char field", "charg": "charg", "chargaff": "char gaff", "chargate": "char gate", "charge": "charge", "charge-": "charge-", "charge-capped": "charge - capped", "charge-capping": "charge - cap ping", "charge-hand": "charge - hand", "charge-payers": "charge - pay ers", "charge-transfer": "charge - trans fer", "chargeable": "charge a ble", "charged": "charged", "chargee": "charge e", "chargees": "charge es", "chargehand": "charge hand", "chargehands": "charge hands", "chargepayers": "charge pay ers", "charger": "charg er", "chargers": "charg ers", "charges": "charg es", "chargin'": "charg in'", "charging": "charg ing", "chargor": "charg or", "chari": "char i", "charial": "char i al", "charibert": "char i bert", "charidee": "char i dee", "charidy": "char i dy", "charig": "char ig", "chariie": "char i ie", "charikar": "char i kar", "charily": "char i ly", "chariman": "char i man", "charimer": "char i mer", "charin'": "char in'", "charing": "char ing", "chariot": "char i ot", "charioteer": "char i o teer", "charioteers": "char i o teers", "chariots": "char i ots", "charis": "char is", "charism": "char ism", "charisma": "char is ma", "charismatic": "char is mat ic", "charismatics": "char is mat ics", "charissa": "char is sa", "charisse": "char is se", "charit": "char it", "charitable": "char i ta ble", "charitably": "char i ta bly", "charitas": "char i tas", "charite": "char i te", "charith": "char ith", "charities": "char i ties", "charity": "char i ty", "chariulf": "char i ulf", "charivari": "char i va ri", "charkham": "chark ham", "charkin": "chark in", "charl": "charl", "charla": "char la", "charlady": "char la dy", "charlatan": "char la tan", "charlatans": "char la tans", "charlbury": "char l bur y", "charle": "char le", "charlecote": "char le cote", "charlee": "char lee", "charleen": "char leen", "charlemagne": "char le magne", "charlen": "char len", "charlene": "char lene", "charleroi": "char le roi", "charlery": "char le ry", "charles-henri": "char les - hen ri", "charleston": "char les ton", "charlestown": "char les town", "charlesworth": "char les worth", "charlet": "char let", "charleton": "char le ton", "charlett": "char lett", "charleville": "char le ville", "charley": "char ley", "charlick": "char lick", "charlie": "char lie", "charlier": "char li er", "charlies": "char lies", "charline": "char line", "charlock": "char lock", "charlot": "char lot", "charlott": "char lott", "charlotte": "char lotte", "charlottenburg": "char lot ten burg", "charlottesville": "char lot tes ville", "charlottetown": "char lotte town", "charlson": "char l son", "charlt'n": "char lt 'n", "charltin": "char l tin", "charlton": "char l ton", "charltons": "char l tons", "charlwood": "char l wood", "charly": "char ly", "charlynch": "char lynch", "charm": "charm", "charmaine": "char maine", "charman": "char man", "charme": "charme", "charmed": "charmed", "charmel": "char mel", "charmer": "charm er", "charmers": "charm ers", "charmes": "charm es", "charmet": "char met", "charmian": "char mi an", "charming": "charm ing", "charmingly": "charm ing ly", "charmion": "char mion", "charmless": "charm less", "charmlessness": "charm less ness", "charmley": "charm ley", "charmm": "charmm", "charmond": "char mond", "charmos": "char mos", "charmouth": "char mouth", "charms": "charms", "charmwood": "charm wood", "charnac": "char nac", "charnay": "char nay", "charnd": "char nd", "charndon": "char nd on", "charnel": "char nel", "charnell": "char nell", "charnels": "char nels", "charnett": "char nett", "charney": "char ney", "charnham": "char n ham", "charniak": "char ni ak", "charnley": "char n ley", "charnock": "char nock", "charnois": "char nois", "charnok": "char nok", "charnos": "char nos", "charnov": "char nov", "charnwood": "char n wood", "charny": "char ny", "charoen": "char o en", "charolais": "char o lais", "charollais": "char ol lais", "charolle": "char ol le", "charon": "char on", "charonia": "char o nia", "charost": "char ost", "charotar": "char o tar", "charoupa": "char ou pa", "charpak": "char pak", "charpentier": "char pen tier", "charpoua": "char pou a", "charpoy": "char poy", "charpoys": "char poys", "charr": "charr", "charrada": "char ra da", "charred": "char red", "charri": "char ri", "charrier": "char ri er", "charring": "char ring", "charrington": "char ring ton", "charron": "char ron", "charry": "char ry", "chars": "chars", "charsh": "char sh", "charsky": "char sky", "charskys": "char skys", "charsley": "char s ley", "chart-based": "chart - based", "chart-room": "chart - room", "chart-topper": "chart - top per", "chart-toppers": "chart - top pers", "chart-topping": "chart - top ping", "charta": "char ta", "chartac": "char tac", "chartbusters": "chart bust ers", "charted": "chart ed", "charter": "char ter", "charter'": "char ter '", "charter-train": "char ter - train", "charterail": "char ter ail", "chartered": "char tered", "charterer": "char ter er", "charterers": "char ter ers", "charterhouse": "char ter house", "chartering": "char ter ing", "charteris": "char ter is", "charters": "char ters", "charth": "charth", "chartham": "char tham", "chartier": "char tier", "charting": "chart ing", "chartism": "char tism", "chartist": "char tist", "chartists": "char tists", "chartley": "char t ley", "charton": "char ton", "chartpak": "char t pak", "chartres": "char tres", "chartreuse": "char treuse", "charts": "charts", "charts-a": "charts - a", "chartsey": "char tsey", "chartson": "char t son", "charturn": "char turn", "chartwell": "char t well", "charve": "char ve", "charvel": "char vel", "charvet": "char vet", "charwal": "char wal", "charwell": "char well", "charwelton": "char wel ton", "charwoman": "char wo man", "charwomen": "char wo men", "chary": "char y", "charybdis": "char yb dis", "charz": "char z", "chas": "chas", "chas'n": "chas 'n", "chasa": "cha sa", "chase": "chase", "chased": "chased", "chasen": "cha sen", "chasers": "chas ers", "chases": "chas es", "chasethe": "chase the", "chasey": "cha sey", "chasgaig": "chas gaig", "chashma": "chash ma", "chashni": "chash ni", "chashnik": "chash nik", "chasid": "cha sid", "chasidic": "cha sid ic", "chasidim": "cha si dim", "chasin": "cha sin", "chasin'": "cha sin'", "chasing": "chas ing", "chasings": "chas ings", "chasm": "chasm", "chasma": "chas ma", "chasms": "chasms"}